[
{
"nombre": "asdf",
"fechaInicio": "Sat Jul 23 00:00:00 CST 2022",
"fechaFin": "Sat Jul 23 00:00:00 CST 2022",
"horaFin": "0",
"minutoFin": "0",
"isNotify": "true",
"state": "false",
"song": "./public/Song.mp3",
"descripcion": "asdf\nasdf\nasdf\nasdf",
"isPeriodic": "false",
"periodo": "0"
},{
"nombre": "asdf",
"fechaInicio": "Sat Jul 23 00:00:00 CST 2022",
"fechaFin": "Sat Jul 23 00:00:00 CST 2022",
"horaFin": "0",
"minutoFin": "0",
"isNotify": "true",
"state": "false",
"song": "./public/Song.mp3",
"descripcion": "asdf\nasdf\nasdf\nasdf",
"isPeriodic": "false",
"periodo": "0"
},{
"nombre": "asdf",
"fechaInicio": "Sat Jul 23 00:00:00 CST 2022",
"fechaFin": "Sat Jul 23 00:00:00 CST 2022",
"horaFin": "23",
"minutoFin": "0",
"isNotify": "true",
"state": "true",
"song": "./public/Song.mp3",
"descripcion": "asdf\nasdf\nasdf\nasdf\n",
"isPeriodic": "false",
"periodo": "0"
},{
"nombre": "asdf",
"fechaInicio": "Sat Jul 23 00:00:00 CST 2022",
"fechaFin": "Sat Jul 23 00:00:00 CST 2022",
"horaFin": "23",
"minutoFin": "0",
"isNotify": "true",
"state": "true",
"song": "./public/Song.mp3",
"descripcion": "asdfa\nasdf\nasdf\nasdf\n",
"isPeriodic": "false",
"periodo": "0"
},{
"nombre": "asdf",
"fechaInicio": "Sat Jul 23 00:00:00 CST 2022",
"fechaFin": "Sat Jul 23 00:00:00 CST 2022",
"horaFin": "23",
"minutoFin": "0",
"isNotify": "true",
"state": "true",
"song": "./public/Song.mp3",
"descripcion": "asdfasdf\nasdf\nasdf\nasdf\n",
"isPeriodic": "false",
"periodo": "0"
}
]